jaxify/__init__.py
jaxify/py.typed
jaxify-0.0.4.dist-info/WHEEL
jaxify-0.0.4.dist-info/METADATA
jaxify-0.0.4.dist-info/RECORD
