Metadata-Version: 2.3
Name: jaxify
Version: 0.0.4
Summary: Write Python. Run JAX
Author: Gabriel S. Gerlero
Author-email: Gabriel S. Gerlero <ggerlero@cimec.unl.edu.ar>
Classifier: Development Status :: 2 - Pre-Alpha
Classifier: Intended Audience :: Developers
Classifier: Programming Language :: Python :: 3 :: Only
Classifier: Programming Language :: Python :: 3.10
Classifier: Programming Language :: Python :: 3.11
Classifier: Programming Language :: Python :: 3.12
Classifier: Programming Language :: Python :: 3.13
Classifier: Programming Language :: Python :: 3.14
Classifier: Topic :: Software Development :: Libraries
Classifier: Typing :: Typed
Classifier: Operating System :: OS Independent
Requires-Dist: jax>=0.5,<0.9
Requires-Python: >=3.10
Project-URL: Homepage, https://github.com/gerlero/jaxify
Project-URL: Repository, https://github.com/gerlero/jaxify
